cuenca_validations/__init__.py
cuenca_validations/card_bins.py
cuenca_validations/errors.py
cuenca_validations/py.typed
cuenca_validations/typing.py
cuenca_validations/validators.py
cuenca_validations/version.py
cuenca_validations/types/__init__.py
cuenca_validations/types/card.py
cuenca_validations/types/enums.py
cuenca_validations/types/files.py
cuenca_validations/types/general.py
cuenca_validations/types/helpers.py
cuenca_validations/types/identities.py
cuenca_validations/types/morals.py
cuenca_validations/types/queries.py
cuenca_validations/types/requests.py
cuenca_validations-2.1.24.dist-info/licenses/LICENSE
tests/__init__.py
tests/test_card.py
tests/test_errors.py
tests/test_helpers.py
tests/test_requests.py
tests/test_statement.py
tests/test_types.py
cuenca_validations-2.1.24.dist-info/METADATA
cuenca_validations-2.1.24.dist-info/WHEEL
cuenca_validations-2.1.24.dist-info/top_level.txt
cuenca_validations-2.1.24.dist-info/RECORD
