Metadata-Version: 2.4
Name: cuenca_validations
Version: 2.1.24
Summary: Cuenca common validations
Home-page: https://github.com/cuenca-mx/cuenca-validations
Author: Cuenca
Author-email: dev@cuenca.com
Classifier: Programming Language :: Python :: 3
Classifier: Programming Language :: Python :: 3.9
Classifier: Programming Language :: Python :: 3.10
Classifier: Programming Language :: Python :: 3.11
Classifier: Programming Language :: Python :: 3.12
Classifier: Programming Language :: Python :: 3.13
Classifier: License :: OSI Approved :: MIT License
Classifier: Operating System :: OS Independent
Requires-Python: >=3.9
License-File: LICENSE
Requires-Dist: clabe>=2.0.0
Requires-Dist: pydantic[email]>=2.10.0
Requires-Dist: pydantic-extra-types>=2.10.0
Requires-Dist: python-dateutil>=2.9.0
Requires-Dist: phonenumbers>=8.13.0
Dynamic: author
Dynamic: author-email
Dynamic: classifier
Dynamic: description
Dynamic: description-content-type
Dynamic: home-page
Dynamic: license-file
Dynamic: requires-dist
Dynamic: requires-python
Dynamic: summary
